purplship/mappers/canpar/__init__.py
purplship/mappers/canpar/mapper.py
purplship/mappers/canpar/proxy.py
purplship/mappers/canpar/settings.py
purplship/providers/canpar/__init__.py
purplship/providers/canpar/address.py
purplship/providers/canpar/error.py
purplship/providers/canpar/pickup/__init__.py
purplship/providers/canpar/pickup/cancel.py
purplship/providers/canpar/pickup/create.py
purplship/providers/canpar/pickup/update.py
purplship/providers/canpar/rate.py
purplship/providers/canpar/shipment/__init__.py
purplship/providers/canpar/shipment/cancel.py
purplship/providers/canpar/shipment/create.py
purplship/providers/canpar/shipment/label.py
purplship/providers/canpar/tracking.py
purplship/providers/canpar/units.py
purplship/providers/canpar/utils.py
purplship.canpar-2022.2.dist-info/WHEEL
purplship.canpar-2022.2.dist-info/METADATA
purplship.canpar-2022.2.dist-info/RECORD
